[
    {
        "SEC": "01",
        "CLASS": "7888",
        "NOMATERIALCOST": "",
        "RESERVECAPACITY": "",
        "CLASSNOTES": "310",
        "TYPE": "LEC",
        "DAYS": "W",
        "TIME": "8-8:45AM",
        "LOCATION": "HHS1-100",
        "INSTRUCTOR": "Johnson D",
        "COMMENT": "Class instruction is: Face to Face - On Campus.",
        "COURSECODE": "M S 102",
        "COURSETITLE": "BASIC LEADERSHIP",
        "Units": "1 Unit"
    },
    {
        "SEC": "01",
        "CLASS": "7889",
        "NOMATERIALCOST": "",
        "RESERVECAPACITY": "",
        "CLASSNOTES": "310",
        "TYPE": "ACT",
        "DAYS": "Th",
        "TIME": "8-10:45AM",
        "LOCATION": "SPA-111",
        "INSTRUCTOR": "Johnson D",
        "COMMENT": "Class instruction is: Face to Face - On Campus.",
        "COURSECODE": "M S 102L",
        "COURSETITLE": "LEADERSHIP LABORATORY",
        "Units": "1 Unit"
    },
    {
        "SEC": "01",
        "CLASS": "7890",
        "NOMATERIALCOST": "",
        "RESERVECAPACITY": "",
        "CLASSNOTES": "310",
        "TYPE": "LEC",
        "DAYS": "W",
        "TIME": "8-10:45AM",
        "LOCATION": "SPA-203",
        "INSTRUCTOR": "Staff",
        "COMMENT": "Class instruction is: Face to Face - On Campus.",
        "COURSECODE": "M S 202",
        "COURSETITLE": "LEADERSHIP AND TEAMWORK",
        "Units": "2 Units"
    },
    {
        "SEC": "01",
        "CLASS": "7891",
        "NOMATERIALCOST": "",
        "RESERVECAPACITY": "",
        "CLASSNOTES": "",
        "TYPE": "ACT",
        "DAYS": "Th",
        "TIME": "8-10:45AM",
        "LOCATION": "SPA-203",
        "INSTRUCTOR": "Staff",
        "COMMENT": "Class instruction is: Face to Face - On Campus.",
        "COURSECODE": "M S 202L",
        "COURSETITLE": "LEADERSHIP LABORATORY",
        "Units": "2 Units"
    },
    {
        "SEC": "01",
        "CLASS": "7892",
        "NOMATERIALCOST": "",
        "RESERVECAPACITY": "",
        "CLASSNOTES": "310",
        "TYPE": "LEC",
        "DAYS": "Tu",
        "TIME": "8-10:45AM",
        "LOCATION": "EN2-103",
        "INSTRUCTOR": "Johnson D",
        "COMMENT": "Class instruction is: Face to Face - On Campus.",
        "COURSECODE": "M S 302",
        "COURSETITLE": "LEADERSHIP & ETHICS",
        "Units": "3 Units"
    },
    {
        "SEC": "01",
        "CLASS": "7893",
        "NOMATERIALCOST": "",
        "RESERVECAPACITY": "",
        "CLASSNOTES": "310",
        "TYPE": "ACT",
        "DAYS": "Th",
        "TIME": "8-10:45AM",
        "LOCATION": "SPA-210",
        "INSTRUCTOR": "Johnson D",
        "COMMENT": "Class instruction is: Face to Face - On Campus.",
        "COURSECODE": "M S 302L",
        "COURSETITLE": "LEADERSHIP LAB",
        "Units": "1 Unit"
    },
    {
        "SEC": "01",
        "CLASS": "7894",
        "NOMATERIALCOST": "",
        "RESERVECAPACITY": "",
        "CLASSNOTES": "310",
        "TYPE": "LEC",
        "DAYS": "Tu",
        "TIME": "8-10:45AM",
        "LOCATION": "LAB-114",
        "INSTRUCTOR": "Chin K",
        "COMMENT": "Class instruction is: Face to Face - On Campus.",
        "COURSECODE": "M S 402",
        "COURSETITLE": "OFFICERSHIP",
        "Units": "3 Units"
    },
    {
        "SEC": "01",
        "CLASS": "7895",
        "NOMATERIALCOST": "",
        "RESERVECAPACITY": "",
        "CLASSNOTES": "310",
        "TYPE": "ACT",
        "DAYS": "Th",
        "TIME": "8-10:45AM",
        "LOCATION": "SPA-212",
        "INSTRUCTOR": "Chin K",
        "COMMENT": "Class instruction is: Face to Face - On Campus.",
        "COURSECODE": "M S 402L",
        "COURSETITLE": "LEADERSHIP LAB",
        "Units": "2 Units"
    },
    {
        "SEC": "04",
        "CLASS": "7230",
        "NOMATERIALCOST": "",
        "RESERVECAPACITY": "",
        "CLASSNOTES": "310",
        "TYPE": "LEC",
        "DAYS": "MW",
        "TIME": "2-3:15PM",
        "LOCATION": "ET-229",
        "INSTRUCTOR": "Johnson D",
        "COMMENT": "Class instruction is: Face to Face - On Campus.",
        "COURSECODE": "M S 411",
        "COURSETITLE": "U.S. MILITARY HISTORY",
        "Units": "3 Units"
    },
    {
        "SEC": "01",
        "CLASS": "1872",
        "NOMATERIALCOST": "",
        "RESERVECAPACITY": "",
        "CLASSNOTES": "",
        "TYPE": "SUP",
        "DAYS": "TBA",
        "TIME": "NA",
        "LOCATION": "ET-233",
        "INSTRUCTOR": "Turner M",
        "COMMENT": "Department Consent RequiredClass instruction is: Face to Face - On Campus.",
        "COURSECODE": "M S 497",
        "COURSETITLE": "INDEPENDENT STUDIES",
        "Units": "1-3 Units"
    }
]