[
    {
        "SEC": "01",
        "CLASS": "3685",
        "NOMATERIALCOST": "",
        "RESERVECAPACITY": "",
        "CLASSNOTES": "1,296,310",
        "TYPE": "SEM",
        "DAYS": "MW",
        "TIME": "9:30-10:45AM",
        "LOCATION": "LA2-104",
        "INSTRUCTOR": "Lunte S",
        "COMMENT": "Class instruction is: Face to Face - On Campus.",
        "COURSECODE": "GERM 101A",
        "COURSETITLE": "FUNDAMENTALS OF GERMAN",
        "Units": "3 Units"
    },
    {
        "SEC": "02",
        "CLASS": "6402",
        "NOMATERIALCOST": "",
        "RESERVECAPACITY": "",
        "CLASSNOTES": "1,296,310",
        "TYPE": "SEM",
        "DAYS": "TuTh",
        "TIME": "9:30-10:45AM",
        "LOCATION": "LA1-314",
        "INSTRUCTOR": "Anderson A",
        "COMMENT": "Class instruction is: Face to Face - On Campus.",
        "COURSECODE": "GERM 101A",
        "COURSETITLE": "FUNDAMENTALS OF GERMAN",
        "Units": "3 Units"
    },
    {
        "SEC": "05",
        "CLASS": "10895",
        "NOMATERIALCOST": "",
        "RESERVECAPACITY": "",
        "CLASSNOTES": "1,296,306",
        "TYPE": "SEM",
        "DAYS": "TuTh",
        "TIME": "5:30-6:45PM",
        "LOCATION": "ONLINE-ONLY",
        "INSTRUCTOR": "Fani D",
        "COMMENT": "Class instruction is: Synch. Online - Meet Times.",
        "COURSECODE": "GERM 101A",
        "COURSETITLE": "FUNDAMENTALS OF GERMAN",
        "Units": "3 Units"
    },
    {
        "SEC": "01",
        "CLASS": "5674",
        "NOMATERIALCOST": "",
        "RESERVECAPACITY": "",
        "CLASSNOTES": "1,296,310",
        "TYPE": "SEM",
        "DAYS": "TuTh",
        "TIME": "11-12:15PM",
        "LOCATION": "LA2-104",
        "INSTRUCTOR": "Muller M",
        "COMMENT": "Class instruction is: Face to Face - On Campus.",
        "COURSECODE": "GERM 101B",
        "COURSETITLE": "FUNDAMENTALS OF GERMAN",
        "Units": "3 Units"
    },
    {
        "SEC": "02",
        "CLASS": "10056",
        "NOMATERIALCOST": "",
        "RESERVECAPACITY": "",
        "CLASSNOTES": "1,296,312",
        "TYPE": "SEM",
        "DAYS": "TuTh",
        "TIME": "11-12:15PM",
        "LOCATION": "ONLINE-ONLY",
        "INSTRUCTOR": "Muller M",
        "COMMENT": "Class instruction is: Synch. Online - Meet Times.",
        "COURSECODE": "GERM 101B",
        "COURSETITLE": "FUNDAMENTALS OF GERMAN",
        "Units": "3 Units"
    },
    {
        "SEC": "01",
        "CLASS": "10057",
        "NOMATERIALCOST": "",
        "RESERVECAPACITY": "",
        "CLASSNOTES": "1,296,310",
        "TYPE": "SEM",
        "DAYS": "MW",
        "TIME": "11-12:15PM",
        "LOCATION": "LA2-104",
        "INSTRUCTOR": "Muller M",
        "COMMENT": "Class instruction is: Face to Face - On Campus.",
        "COURSECODE": "GERM 201A",
        "COURSETITLE": "INTERMEDIATE GERMAN",
        "Units": "3 Units"
    },
    {
        "SEC": "02",
        "CLASS": "10058",
        "NOMATERIALCOST": "",
        "RESERVECAPACITY": "",
        "CLASSNOTES": "1,296,312",
        "TYPE": "SEM",
        "DAYS": "MW",
        "TIME": "11-12:15PM",
        "LOCATION": "ONLINE-ONLY",
        "INSTRUCTOR": "Muller M",
        "COMMENT": "Class instruction is: Synch. Online - Meet Times.",
        "COURSECODE": "GERM 201A",
        "COURSETITLE": "INTERMEDIATE GERMAN",
        "Units": "3 Units"
    },
    {
        "SEC": "01",
        "CLASS": "8232",
        "NOMATERIALCOST": "",
        "RESERVECAPACITY": "",
        "CLASSNOTES": "1,296,310",
        "TYPE": "SEM",
        "DAYS": "TuTh",
        "TIME": "9:30-10:45AM",
        "LOCATION": "LA2-104",
        "INSTRUCTOR": "Blankenship R",
        "COMMENT": "Class instruction is: Face to Face - On Campus.",
        "COURSECODE": "GERM 201B",
        "COURSETITLE": "INTERMEDIATE GERMAN",
        "Units": "3 Units"
    },
    {
        "SEC": "02",
        "CLASS": "10059",
        "NOMATERIALCOST": "",
        "RESERVECAPACITY": "",
        "CLASSNOTES": "1,296,312",
        "TYPE": "SEM",
        "DAYS": "TuTh",
        "TIME": "9:30-10:45AM",
        "LOCATION": "ONLINE-ONLY",
        "INSTRUCTOR": "Blankenship R",
        "COMMENT": "Class instruction is: Synch. Online - Meet Times.",
        "COURSECODE": "GERM 201B",
        "COURSETITLE": "INTERMEDIATE GERMAN",
        "Units": "3 Units"
    },
    {
        "SEC": "03",
        "CLASS": "10893",
        "NOMATERIALCOST": "",
        "RESERVECAPACITY": "",
        "CLASSNOTES": "1,310",
        "TYPE": "SEM",
        "DAYS": "MW",
        "TIME": "3:30-4:45PM",
        "LOCATION": "LA2-101B",
        "INSTRUCTOR": "Muller M",
        "COMMENT": "Class instruction is: Face to Face - On Campus.",
        "COURSECODE": "GERM 305",
        "COURSETITLE": "ADVANCED GERMAN CONVERSATION",
        "Units": "3 Units"
    },
    {
        "SEC": "01",
        "CLASS": "5504",
        "NOMATERIALCOST": "",
        "RESERVECAPACITY": "",
        "CLASSNOTES": "1,310",
        "TYPE": "SEM",
        "DAYS": "TuTh",
        "TIME": "3:30-4:45PM",
        "LOCATION": "LAB-200",
        "INSTRUCTOR": "Blankenship R",
        "COMMENT": "Class instruction is: Face to Face - On Campus.",
        "COURSECODE": "GERM 397",
        "COURSETITLE": "MARX, NIETZSCHE, FREUD",
        "Units": "3 Units"
    },
    {
        "SEC": "01",
        "CLASS": "10061",
        "NOMATERIALCOST": "",
        "RESERVECAPACITY": "",
        "CLASSNOTES": "1,13,310",
        "TYPE": "SEM",
        "DAYS": "MW",
        "TIME": "7-8:15PM",
        "LOCATION": "LA2-101B",
        "INSTRUCTOR": "Blankenship R",
        "COMMENT": "Class instruction is: Face to Face - On Campus.",
        "COURSECODE": "GERM 459",
        "COURSETITLE": "GERMAN LITERATURE 1890 TO 1945",
        "Units": "3 Units"
    },
    {
        "SEC": "01",
        "CLASS": "2024",
        "NOMATERIALCOST": "",
        "RESERVECAPACITY": "",
        "CLASSNOTES": "1,29,310",
        "TYPE": "LEC",
        "DAYS": "Th",
        "TIME": "5-6:50PM",
        "LOCATION": "LA3-120",
        "INSTRUCTOR": "Petrus A",
        "COMMENT": "Class instruction is: Face to Face - On Campus.Class offered with CINE-457-01",
        "COURSECODE": "GERM 480",
        "COURSETITLE": "GERMAN CINEMA",
        "Units": "3 Units"
    },
    {
        "SEC": "02",
        "CLASS": "8430",
        "NOMATERIALCOST": "",
        "RESERVECAPACITY": "",
        "CLASSNOTES": "1,29,310",
        "TYPE": "ACT",
        "DAYS": "Th",
        "TIME": "7-8:50PM",
        "LOCATION": "LA3-120",
        "INSTRUCTOR": "Petrus A",
        "COMMENT": "Class instruction is: Face to Face - On Campus.Class offered with CINE-457-02",
        "COURSECODE": "GERM 480",
        "COURSETITLE": "GERMAN CINEMA",
        "Units": "3 Units"
    },
    {
        "SEC": "01",
        "CLASS": "2965",
        "NOMATERIALCOST": "",
        "RESERVECAPACITY": "",
        "CLASSNOTES": "1,3,305",
        "TYPE": "SUP",
        "DAYS": "TBA",
        "TIME": "NA",
        "LOCATION": "ONLINE-ONLY",
        "INSTRUCTOR": "Staff",
        "COMMENT": "Department Consent RequiredClass instruction is: Asynch. Online-No Meet Times.",
        "COURSECODE": "GERM 494",
        "COURSETITLE": "INTERNSHIP IN GERMAN",
        "Units": "1-3 Units"
    },
    {
        "SEC": "01",
        "CLASS": "10063",
        "NOMATERIALCOST": "",
        "RESERVECAPACITY": "",
        "CLASSNOTES": "1,13,310",
        "TYPE": "SEM",
        "DAYS": "MW",
        "TIME": "5:30-6:45PM",
        "LOCATION": "LA2-101B",
        "INSTRUCTOR": "Hempel-Lamer N",
        "COMMENT": "German DramaClass instruction is: Face to Face - On Campus.",
        "COURSECODE": "GERM 498",
        "COURSETITLE": "S TOPICS GERMAN",
        "Units": "3 Units"
    },
    {
        "SEC": "01",
        "CLASS": "3772",
        "NOMATERIALCOST": "",
        "RESERVECAPACITY": "",
        "CLASSNOTES": "1,3,305",
        "TYPE": "SUP",
        "DAYS": "TBA",
        "TIME": "NA",
        "LOCATION": "ONLINE-ONLY",
        "INSTRUCTOR": "Staff",
        "COMMENT": "Department Consent RequiredClass instruction is: Asynch. Online-No Meet Times.",
        "COURSECODE": "GERM 499",
        "COURSETITLE": "DIRECTED STUDIES",
        "Units": "1-3 Units"
    },
    {
        "SEC": "01",
        "CLASS": "10062",
        "NOMATERIALCOST": "",
        "RESERVECAPACITY": "",
        "CLASSNOTES": "1,13,310",
        "TYPE": "SEM",
        "DAYS": "MW",
        "TIME": "7-8:15PM",
        "LOCATION": "LA2-101B",
        "INSTRUCTOR": "Blankenship R",
        "COMMENT": "Class instruction is: Face to Face - On Campus.",
        "COURSECODE": "GERM 559",
        "COURSETITLE": "GERMAN LITERATURE 1890 TO 1945",
        "Units": "3 Units"
    },
    {
        "SEC": "01",
        "CLASS": "10064",
        "NOMATERIALCOST": "",
        "RESERVECAPACITY": "",
        "CLASSNOTES": "1,13,310",
        "TYPE": "SEM",
        "DAYS": "MW",
        "TIME": "5:30-6:45PM",
        "LOCATION": "LA2-101B",
        "INSTRUCTOR": "Hempel-Lamer N",
        "COMMENT": "German DramaClass instruction is: Face to Face - On Campus.",
        "COURSECODE": "GERM 598",
        "COURSETITLE": "S TOPICS GERMAN",
        "Units": "3 Units"
    },
    {
        "SEC": "01",
        "CLASS": "3767",
        "NOMATERIALCOST": "",
        "RESERVECAPACITY": "",
        "CLASSNOTES": "1,3,305",
        "TYPE": "SUP",
        "DAYS": "TBA",
        "TIME": "NA",
        "LOCATION": "ONLINE-ONLY",
        "INSTRUCTOR": "Staff",
        "COMMENT": "Department Consent RequiredClass instruction is: Asynch. Online-No Meet Times.",
        "COURSECODE": "GERM 599",
        "COURSETITLE": "DIRECTED STUDIES",
        "Units": "1-3 Units"
    }
]